DLMS_SPODES/__init__.py
DLMS_SPODES/configEN.ini
DLMS_SPODES/config_parser.py
DLMS_SPODES/cosem_pdu.py
DLMS_SPODES/enums.py
DLMS_SPODES/exceptions.py
DLMS_SPODES/firmwares.py
DLMS_SPODES/literals.py
DLMS_SPODES/pardata.py
DLMS_SPODES/pdu_enums.py
DLMS_SPODES/py.typed
DLMS_SPODES/relation_to_OBIS.py
DLMS_SPODES/settings.py
DLMS_SPODES/Values/__init__.py
DLMS_SPODES/Values/EN/__init__.py
DLMS_SPODES/Values/EN/actors.py
DLMS_SPODES/Values/EN/relation_to_obis_names.py
DLMS_SPODES/Values/RU/__init__.py
DLMS_SPODES/Values/RU/actors.py
DLMS_SPODES/Values/RU/relation_to_obis_names.py
DLMS_SPODES/cosem_interface_classes/__class_init__.py
DLMS_SPODES/cosem_interface_classes/__init__.py
DLMS_SPODES/cosem_interface_classes/a_parameter.py
DLMS_SPODES/cosem_interface_classes/activity_calendar.py
DLMS_SPODES/cosem_interface_classes/arbitrator.py
DLMS_SPODES/cosem_interface_classes/attr_indexes.py
DLMS_SPODES/cosem_interface_classes/clock.py
DLMS_SPODES/cosem_interface_classes/collection.py
DLMS_SPODES/cosem_interface_classes/cosem_interface_class.py
DLMS_SPODES/cosem_interface_classes/data.py
DLMS_SPODES/cosem_interface_classes/disconnect_control.py
DLMS_SPODES/cosem_interface_classes/extended_register.py
DLMS_SPODES/cosem_interface_classes/gprs_modem_setup.py
DLMS_SPODES/cosem_interface_classes/iec_local_port_setup.py
DLMS_SPODES/cosem_interface_classes/ipv4_setup.py
DLMS_SPODES/cosem_interface_classes/limiter.py
DLMS_SPODES/cosem_interface_classes/ln_pattern.py
DLMS_SPODES/cosem_interface_classes/obis.py
DLMS_SPODES/cosem_interface_classes/overview.py
DLMS_SPODES/cosem_interface_classes/parameter.py
DLMS_SPODES/cosem_interface_classes/parameters.py
DLMS_SPODES/cosem_interface_classes/register.py
DLMS_SPODES/cosem_interface_classes/register_monitor.py
DLMS_SPODES/cosem_interface_classes/reports.py
DLMS_SPODES/cosem_interface_classes/schedule.py
DLMS_SPODES/cosem_interface_classes/script_table.py
DLMS_SPODES/cosem_interface_classes/single_action_schedule.py
dlms_spodes-0.87.11.dist-info/METADATA
dlms_spodes-0.87.11.dist-info/WHEEL
dlms_spodes-0.87.11.dist-info/top_level.txt
dlms_spodes-0.87.11.dist-info/RECORD
