Metadata-Version: 2.4
Name: DLMS_SPODES
Version: 0.87.11
Summary: dlms-spodes
Author-email: Serj Kotilevski <youserj@outlook.com>
Project-URL: Source, https://github.com/youserj/DlmsSPODES-project
Keywords: dlms
Classifier: Programming Language :: Python :: 3
Classifier: License :: OSI Approved :: MIT License
Classifier: Operating System :: OS Independent
Requires-Python: >=3.12
Requires-Dist: pydantic>=2.11
Requires-Dist: cryptography>=45.0
Requires-Dist: semver>=3.0
Requires-Dist: typing-extensions>=4.12.2
Requires-Dist: StructResult>=0.9.2
Requires-Dist: numpy>=2.3.2
Provides-Extra: dev
Requires-Dist: mypy>=1.5.0; extra == "dev"
Requires-Dist: ruff>=0.11; extra == "dev"
Requires-Dist: types-requests; extra == "dev"
Requires-Dist: build>=1.3; extra == "dev"
Requires-Dist: twine; extra == "dev"
